detect_mask/Mask.py
detect_mask/__init__.py
detect_mask/export.pkl
detect_mask/haarcascade_frontalface_default.xml
detect_mask-0.7.0.dist-info/LICENSE
detect_mask-0.7.0.dist-info/METADATA
detect_mask-0.7.0.dist-info/WHEEL
detect_mask-0.7.0.dist-info/top_level.txt
detect_mask-0.7.0.dist-info/RECORD
