Metadata-Version: 2.1
Name: detect-mask
Version: 0.7.0
Summary: Python Package for detecting masks in the input Photos ,Pull out the camera for real time mask detection
Home-page: https://github.com/Jash271/Detect_Mask
Author: Jash Shah
Author-email: shahjash271@gmail.com
License: MIT
Platform: UNKNOWN
Classifier: Development Status :: 4 - Beta
Classifier: License :: OSI Approved :: MIT License
Classifier: Programming Language :: Python
Classifier: Topic :: Software Development :: Libraries
Classifier: Topic :: Software Development :: Libraries :: Python Modules
Classifier: Intended Audience :: Developers
Requires-Python: >=3.6.8
License-File: LICENSE
Requires-Dist: opencv-python
